topshape/__init__.py
topshape/topshape.py
topshape-1.0.0.data/scripts/toppy
topshape-1.0.0.dist-info/DESCRIPTION.rst
topshape-1.0.0.dist-info/METADATA
topshape-1.0.0.dist-info/RECORD
topshape-1.0.0.dist-info/WHEEL
topshape-1.0.0.dist-info/metadata.json
topshape-1.0.0.dist-info/top_level.txt
