Metadata-Version: 2.0
Name: topshape
Version: 1.0.0
Summary: Library for easily creating text interfaces that look like Linux's top program.
Home-page: https://github.com/mchlumsky/topshape
Author: Martin Chlumsky
Author-email: martin.chlumsky@gmail.com
License: MIT license
Keywords: topshape
Platform: UNKNOWN
Classifier: Development Status :: 5 - Production/Stable
Classifier: Intended Audience :: Developers
Classifier: License :: OSI Approved :: MIT License
Classifier: Natural Language :: English
Classifier: Programming Language :: Python :: 2
Classifier: Programming Language :: Python :: 2.7
Classifier: Programming Language :: Python :: 3
Classifier: Programming Language :: Python :: 3.3
Classifier: Programming Language :: Python :: 3.4
Classifier: Programming Language :: Python :: 3.5
Classifier: Programming Language :: Python :: 3.6
Requires-Dist: psutil
Requires-Dist: urwid
